coincident/__init__.py
coincident/_utils.py
coincident/_version.py
coincident/pcd_fixtures.py
coincident/py.typed
coincident/datasets/__init__.py
coincident/datasets/csda.py
coincident/datasets/general.py
coincident/datasets/maxar.py
coincident/datasets/nasa.py
coincident/datasets/neon.py
coincident/datasets/opentopo.py
coincident/datasets/planetary_computer.py
coincident/datasets/usgs.py
coincident/io/__init__.py
coincident/io/download.py
coincident/io/sliderule.py
coincident/io/xarray.py
coincident/overlaps/__init__.py
coincident/plot/__init__.py
coincident/plot/matplotlib.py
coincident/plot/utils.py
coincident/scripts/__init__.py
coincident/scripts/generate_pcd.py
coincident/search/__init__.py
coincident/search/main.py
coincident/search/neon_api.py
coincident/search/opentopo_api.py
coincident/search/stac.py
coincident/search/swath_polygons.csv
coincident/search/wesm.py
coincident-0.4.1.dist-info/METADATA
coincident-0.4.1.dist-info/WHEEL
coincident-0.4.1.dist-info/licenses/LICENSE
coincident-0.4.1.dist-info/RECORD
