Metadata-Version: 2.4
Name: coincident
Version: 0.4.1
Summary: Search and analysis of STV Precursor Coincident Datasets
Project-URL: Homepage, https://github.com/uw-cryo/coincident
Project-URL: Bug Tracker, https://github.com/uw-cryo/coincident/issues
Project-URL: Discussions, https://github.com/uw-cryo/coincident/discussions
Project-URL: Changelog, https://github.com/uw-cryo/coincident/releases
Author-email: Scott Henderson <scottyh@uw.edu>, David Shean <dshean@uw.edu>, Jack Hayes <jehayes@uw.edu>
License: Copyright 2024 Scott Henderson
License-File: LICENSE
Classifier: Development Status :: 1 - Planning
Classifier: Intended Audience :: Developers
Classifier: Intended Audience :: Science/Research
Classifier: License :: OSI Approved :: MIT License
Classifier: Operating System :: OS Independent
Classifier: Programming Language :: Python
Classifier: Programming Language :: Python :: 3
Classifier: Programming Language :: Python :: 3 :: Only
Classifier: Programming Language :: Python :: 3.10
Classifier: Programming Language :: Python :: 3.11
Classifier: Programming Language :: Python :: 3.12
Classifier: Topic :: Scientific/Engineering
Classifier: Typing :: Typed
Requires-Python: >=3.10
Requires-Dist: aiobotocore[boto3]
Requires-Dist: geopandas>=1.0
Requires-Dist: ipykernel>=6.29
Requires-Dist: ipywidgets<9,>=8.1.7
Requires-Dist: matplotlib>=3.10
Requires-Dist: maxar-platform>=1.0.7
Requires-Dist: odc-stac>=0.4
Requires-Dist: pyarrow>=19.0
Requires-Dist: pystac-client>=0.8
Requires-Dist: requests>=2.32
Requires-Dist: rioxarray>=0.19
Requires-Dist: s3fs>=2025.3
Requires-Dist: scipy>=1.15.2
Requires-Dist: sliderule>=4.12
Requires-Dist: stac-asset>=0.4.5
Requires-Dist: stac-geoparquet>=0.6
Requires-Dist: tqdm<5,>=4.67.1
Provides-Extra: dev
Requires-Dist: cql2; extra == 'dev'
Requires-Dist: mypy>=1.11; extra == 'dev'
Requires-Dist: pre-commit>=4; extra == 'dev'
Requires-Dist: pylint>=3.3; extra == 'dev'
Requires-Dist: pytest-cov>=3; extra == 'dev'
Requires-Dist: pytest>=6; extra == 'dev'
Provides-Extra: docs
Requires-Dist: folium; extra == 'docs'
Requires-Dist: mapclassify; extra == 'docs'
Requires-Dist: myst-nb; extra == 'docs'
Requires-Dist: myst-parser>=0.13; extra == 'docs'
Requires-Dist: pydata-sphinx-theme<0.17,>=0.16.0; extra == 'docs'
Requires-Dist: sphinx-autodoc-typehints; extra == 'docs'
Requires-Dist: sphinx-copybutton; extra == 'docs'
Requires-Dist: sphinx-design; extra == 'docs'
Requires-Dist: sphinx>=8.0; extra == 'docs'
